PAScual/CHNconvert.py
PAScual/CHNfiles.py
PAScual/CommandsTableMV.py
PAScual/ComponentTableMV.py
PAScual/PASCommandProcess.py
PAScual/PAScual.py
PAScual/PAScualGUI.py
PAScual/PAScual_input.py
PAScual/PASoptions.py
PAScual/ParamWizard.py
PAScual/PlotGraphWidget.py
PAScual/ROISelectorDlg.py
PAScual/SpecFiles.py
PAScual/SpectraTableMV.py
PAScual/TEcalc.py
PAScual/TEcalcGUI.py
PAScual/__init__.py
PAScual/plothistory.py
PAScual/pyTaoEldrup.py
PAScual/release.py
PAScual/testinst.py
PAScual/ui.py
PAScual/icons/CRbutton_ok.png
PAScual/icons/CRcalc.png
PAScual/icons/CRdelete.png
PAScual/icons/CRfileopen.png
PAScual/icons/CRfilesave.png
PAScual/icons/CRmix_audio.png
PAScual/icons/CRplayer_end.png
PAScual/icons/CRplayer_pause.png
PAScual/icons/CRplayer_play.png
PAScual/icons/CRplayer_stop.png
PAScual/icons/PAScual-250x250.png
PAScual/icons/PAScual-32x32.png
PAScual/icons/PAScual-64x64.png
PAScual/icons/PAScual-big.png
PAScual/icons/TaoEldrup32x32.png
PAScual/icons/TaoEldrup64x64.png
PAScual/icons/Wizard.png
PAScual/icons/advancedsettings.png
PAScual/icons/agt_update_recommended.png
PAScual/icons/checkall.png
PAScual/icons/checkmarked.png
PAScual/icons/checknone.png
PAScual/icons/greenbullet.png
PAScual/icons/khelpcenter.png
PAScual/icons/kspread.png
PAScual/icons/package_editors.png
PAScual/icons/questionmark.png
PAScual/icons/qwtplot.png
PAScual/icons/redbullet.png
PAScual/icons/sigma.png
PAScual/icons/yellowbullet.png
PAScual/ui/AddCompsWidget.ui
PAScual/ui/FitparWidget.ui
PAScual/ui/OptionsDlg.ui
PAScual/ui/PAScualGUI.ui
PAScual/ui/TEcalcDialog.ui
PAScual-3.0.3.dist-info/LICENSE.txt
PAScual-3.0.3.dist-info/METADATA
PAScual-3.0.3.dist-info/WHEEL
PAScual-3.0.3.dist-info/entry_points.txt
PAScual-3.0.3.dist-info/top_level.txt
PAScual-3.0.3.dist-info/RECORD
