Metadata-Version: 2.1
Name: PAScual
Version: 3.0.3
Summary: Positron Annihilation Spectroscopy data analysis
Home-page: https://github.com/cpascual/PAScual
Author: Carlos Pascual-Izarra
Author-email: cpascual@users.sourceforge.net
License: GPLv3
Keywords: science PALS PAS positron annihilation fit
Platform: UNKNOWN
Classifier: Development Status :: 5 - Production/Stable
Classifier: Environment :: X11 Applications :: Qt
Classifier: Environment :: Win32 (MS Windows)
Classifier: Intended Audience :: Science/Research
Classifier: License :: OSI Approved :: GNU General Public License v3 or later (GPLv3+)
Classifier: Natural Language :: English
Classifier: Operating System :: OS Independent
Classifier: Programming Language :: Python :: 3 :: Only
Classifier: Topic :: Scientific/Engineering
License-File: LICENSE.txt
Requires-Dist: PythonQwt
Requires-Dist: numpy
Requires-Dist: pyqt5
Requires-Dist: scipy
